{"stats":{"minecraft:custom":{"minecraft:jump":1712,"minecraft:open_chest":94,"minecraft:time_since_rest":768445,"minecraft:inspect_hopper":8,"minecraft:play_one_minute":768445,"minecraft:crouch_one_cm":1047,"minecraft:inspect_dropper":4,"minecraft:leave_game":22,"minecraft:sprint_one_cm":448152,"minecraft:time_since_death":768445,"minecraft:walk_one_cm":1195679,"minecraft:sneak_time":469,"minecraft:bell_ring":909,"minecraft:interact_with_lectern":30,"minecraft:fall_one_cm":35105,"minecraft:fly_one_cm":195692,"minecraft:inspect_dispenser":5},"minecraft:used":{"minecraft:yellow_concrete":35,"minecraft:oak_sign":2,"minecraft:green_concrete":59,"minecraft:black_concrete":48,"minecraft:white_concrete":72,"minecraft:blue_concrete":100,"minecraft:red_concrete":17}},"DataVersion":2580}